{
  "name": "progressionA_workshop",
  "tutorial_level_file": "levels/tutorial_level.json",
  "slots": [
    {
      "slot": 1,
      "status": "reserved",
      "label": "TUTORIAL"
    },
    {
      "slot": 2,
      "level_file": "levels/image08_level_editor.json"
    },
    {
      "slot": 3,
      "level_file": "levels/susanne_level_2_manager_ok.json"
    },
    {
      "slot": 4,
      "level_file": "levels/susanne_level_3_manager_ok.json"
    },
    {
      "slot": 5,
      "level_file": "levels/susanne_level_4_manager_ok.json"
    },
    {
      "slot": 6,
      "level_file": "levels/image06_level_editor.json"
    },
    {
      "slot": 7,
      "level_file": "levels/image27_level_editor.json"
    },
    {
      "slot": 8,
      "level_file": "levels/susanne_level_5_manager_ok.json"
    },
    {
      "slot": 9,
      "level_file": "levels/susanne_level_1_manager_ok.json"
    },
    {
      "slot": 10,
      "level_file": "levels/image30_level_editor.json"
    }
  ]
}
