{
  "id": "lvl_039_image30_level_editor",
  "difficultyTier": 2,
  "gridSize": {
    "cols": 4,
    "rows": 4
  },
  "moves": 8,
  "pairs": [
    {
      "type": "red",
      "a": {
        "x": 0,
        "y": 3
      },
      "b": {
        "x": 3,
        "y": 2
      }
    },
    {
      "type": "cyan",
      "a": {
        "x": 1,
        "y": 0
      },
      "b": {
        "x": 0,
        "y": 2
      }
    }
  ],
  "blockers": [
    {
      "x": 3,
      "y": 0
    }
  ],
  "solutionCount": 20,
  "targetDensity": "HIGH",
  "goldenPath": {
    "A": [
      [
        3,
        0
      ],
      [
        2,
        3
      ]
    ],
    "B": [
      [
        0,
        1
      ],
      [
        2,
        0
      ]
    ]
  },
  "meta": {
    "generation_attempts": 1,
    "failed_checks": [],
    "canonical_id": "lvl_039",
    "canonical_file": "lvl_039_image30_level_editor.json",
    "canonical_slug": "image30_level_editor",
    "canonicalized_at": "2026-03-12T09:14:58.426Z",
    "previous_files": [
      "level_toolkit_web/workshop_jsons/image30_level_editor.json",
      "level_toolkit_web/workshop_jsons/new_level10_a.json",
      "level_toolkit_web/workshop_jsons_game_unique/image30_level_editor.json",
      "levels/image30_level_editor.json",
      "levels/new_level10_a.json",
      "levels/standalone/image30_level_editor.json",
      "niveles_workshop/jsons/image30_level_editor.json"
    ]
  },
  "validation": {
    "solvable": true,
    "density_match": true,
    "early_mistake_detection": true,
    "no_isolated_pairs": true,
    "no_late_dead_ends": true,
    "curve_integrity": true
  }
}